rtl/mac.v
module mac (
    input  signed [7:0]  a,
    input  signed [7:0]  b,
    input  signed [31:0] accum_in,

    output signed [31:0] accum_out
);

assign accum_out = accum_in + (a * b);

endmodule

rtl/sram_C.v
module SRAM_C(dataIn,dataOut,Addr,CS,WE,RD, Clk );

// parameters for the width 
parameter ADR   = 10;

parameter DAT   = 32;

parameter DPTH  = 1024;

//ports
input   [DAT-1:0]  dataIn;

output reg [DAT-1:0]  dataOut;

input   [ADR-1:0]  Addr;

input CS,WE,RD,Clk;

reg signed[DAT-1:0] SRAMs [DPTH-1:0];

always @ (posedge Clk)

begin

 if (CS == 1'b1) begin

  if (WE == 1'b1 && RD == 1'b0) begin

   SRAMs [Addr] = dataIn;

  end

  else if (RD == 1'b1 && WE == 1'b0) begin

   dataOut = SRAMs [Addr]; 

  end

  else;

 end

 else;

end
endmodule

rtl/sram_B.v
module SRAM_B(dataIn,dataOut,Addr,CS,WE,RD, Clk );

// parameters for the width 
parameter ADR   = 12;

parameter DAT   = 64;

parameter DPTH  = 4096;

//ports
input   [DAT-1:0]  dataIn;

output reg [DAT-1:0]  dataOut;

input   [ADR-1:0]  Addr;

input CS,WE,RD,Clk;


reg [DAT-1:0] SRAMs [0:DPTH-1];

always @ (posedge Clk)

begin

 if (CS == 1'b1) begin

  if (WE == 1'b1 && RD == 1'b0) begin

   SRAMs [Addr] = dataIn;

  end

  else if (RD == 1'b1 && WE == 1'b0) begin

   dataOut = SRAMs [Addr]; 

  end

  else;

 end

 else;

end
endmodule

rtl/sram_A.v
module SRAM_A(dataIn,dataOut,Addr,CS,WE,RD, Clk );

// parameters for the width 
parameter ADR   = 10;

parameter DAT   = 8;

parameter DPTH  = 1024;

//ports
input   [DAT-1:0]  dataIn;

output reg [DAT-1:0]  dataOut;

input   [ADR-1:0]  Addr;

input CS,WE,RD,Clk;

reg [DAT-1:0] SRAMs [0:DPTH-1];

always @ (posedge Clk)

begin

 if (CS == 1'b1) begin

  if (WE == 1'b1 && RD == 1'b0) begin

   SRAMs [Addr] = dataIn;

  end

  else if (RD == 1'b1 && WE == 1'b0) begin

   dataOut = SRAMs [Addr]; 

  end

  else;

 end

 else;

end
endmodule

rtl/gemm_accelerator.v
module gemm_accelerator(
    input clk,
    input rst_n,

    input start,

    input [9:0]  A_base,
    input [11:0] B_base,
    input [9:0]  C_base,

    input [15:0] M,
    input [15:0] K,
    input [15:0] N,

    output reg done
);

//regs to store the inputs
reg [9:0]  A_base_r;
reg [11:0] B_base_r;
reg [9:0]  C_base_r;

reg [15:0] M_r;
reg [15:0] K_r;
reg [15:0] N_r;

//FSM variables
localparam IDLE    = 3'd0;
localparam INIT    = 3'd1;
localparam COMPUTE = 3'd2;
localparam WRITE   = 3'd3;
localparam DONE    = 3'd4;

reg [2:0] state;
reg [2:0] next_state;

//sram I/O
reg [7:0] sram_A_din;
wire [7:0] sram_A_dout;
reg [9:0] sram_A_addr;
reg [0:0] sram_A_CS, sram_A_WE, sram_A_RD; 

reg [63:0] sram_B_din;
wire [63:0] sram_B_dout;
reg [11:0] sram_B_addr;
reg [0:0] sram_B_CS, sram_B_WE, sram_B_RD; 

reg [31:0] sram_C_din;
wire [31:0] sram_C_dout;
reg [9:0] sram_C_addr;
reg [0:0] sram_C_CS, sram_C_WE, sram_C_RD; 

//counters to loop through the matrix
reg [15:0] i; //iterates through rows of Matrix A
reg [15:0] j; //iterates through columns of Matrix B, N_MAC columns at once 
reg [15:0] k; //iterates through elements in a single row of Matrix A or column of Matrix B
reg [15:0] i_max; // i_max = M-1 
reg [15:0] j_max; // j_max = ceil(N/N_MAC)-1
reg [15:0] k_max; // k_max = K-1

//counter to loop through the MAC units during multicycle WRITE state
reg [3:0] mac_id;

//parameters
localparam N_MAC = 8; // number of parallel mac units
integer idx;

//MAC I/O
reg signed [7:0] A_reg;
reg signed [7:0] B_reg [N_MAC-1:0];
reg signed [31:0] accum_in [N_MAC-1:0];
wire signed [31:0] mac_out [N_MAC-1:0];
reg signed [31:0] accum_reg [N_MAC-1:0];

//Pipelined valid signals 
reg issue_valid; //address issued to sram_A and sram_B in that cycle is valid
reg data_valid;  //data in sram_A_dout and sram_B_dout regs are valid in that cycle
reg mac_valid;   //combinational MAC output is valid

//trackers for last compute cycles
reg last_issue; //address corresponding to the final k value is issued 
reg last_data;  //data corresponding to the last fetch is available in sram_A_dout and sram_B_dout
reg last_mac;   //combinational MAC output for the last fetch is ready

//tracks the completion of WRITE state
reg write_done;

//SRAM instances
SRAM_A sram_A(
    .dataIn(sram_A_din),
    .dataOut(sram_A_dout),
    .Addr(sram_A_addr),
    .CS(sram_A_CS),
    .WE(sram_A_WE),
    .RD(sram_A_RD), 
    .Clk(clk) 
);

SRAM_B sram_B(
    .dataIn(sram_B_din),
    .dataOut(sram_B_dout),
    .Addr(sram_B_addr),
    .CS(sram_B_CS),
    .WE(sram_B_WE),
    .RD(sram_B_RD),
    .Clk(clk) 
);

SRAM_C sram_C(
    .dataIn(sram_C_din),
    .dataOut(sram_C_dout),
    .Addr(sram_C_addr),
    .CS(sram_C_CS),
    .WE(sram_C_WE),
    .RD(sram_C_RD), 
    .Clk(clk) 
);

//MAC instances
genvar g;
generate
    for(g = 0; g < N_MAC; g = g + 1) begin : MAC_ARRAY
        mac mac_inst (
            .a(A_reg),
            .b(B_reg[g]),
            .accum_in(accum_in[g]),
            .accum_out(mac_out[g])
        );
    end
endgenerate

//state transistion
always @(posedge clk or negedge rst_n) begin
    if(!rst_n) begin
        state <= IDLE;
    end
    else begin
        state <= next_state;
    end
end

//data path
always @(posedge clk or negedge rst_n) begin
    if(!rst_n) begin
        done <= 0; 

        A_base_r <= 0;
        B_base_r <= 0;
        C_base_r <= 0;

        M_r <= 0;
        K_r <= 0;
        N_r <= 0;

        i_max <= 0;
        j_max <= 0;
        k_max <= 0;

        i <= 0;
        j <= 0;
        k <= 0;
        mac_id <= 0;

        issue_valid <= 0;
        data_valid <= 0;
        mac_valid <= 0;

        last_issue <= 0;
        last_data <= 0;
        last_mac <= 0;

        sram_A_addr <= 0;
        sram_B_addr <= 0;
        sram_C_addr <= 0;
        sram_C_din <= 0;

        sram_A_CS <= 0;
        sram_A_WE <= 0;
        sram_A_RD <= 0;

        sram_B_CS <= 0;
        sram_B_WE <= 0;
        sram_B_RD <= 0;

        sram_C_CS <= 0;
        sram_C_WE <= 0;
        sram_C_RD <= 0;

        A_reg <= 0;
        for(idx = 0; idx < N_MAC; idx = idx + 1) begin
            B_reg[idx] <= 0;
            accum_reg[idx] <= 0;
        end
    end
    else begin
        case(state) 
            IDLE:begin //hold reg values from done until start, load the new inputs when start
                if(start) begin
                    done <= 0; //done=1 until start pulse is received
                    A_base_r <= A_base;
                    B_base_r <= B_base;
                    C_base_r <= C_base;
                    M_r <= M;
                    K_r <= K;
                    N_r <= N;
                end 
            end
            INIT:begin //feed all the regs with known reset values
                i_max <= M_r-1;
                j_max <= ((N_r+N_MAC-1)/N_MAC)-1;
                k_max <= K_r-1;

                i <= 0;
                j <= 0;
                k <= 0;

                issue_valid <= 1; //issue_valid = 1 in first compute cycle as the address(combinational) for k=0 is issued
                data_valid <= 0;
                mac_valid <= 0;

                if(K_r==1) //corner case when k_max = K-1 = 0
                    last_issue <= 1;
                else
                    last_issue <= 0;
                last_data <= 0;
                last_mac <= 0;

                sram_C_addr <= 0;
                sram_C_din <= 0;
                mac_id <= 0;

                sram_C_CS <= 0;
                sram_C_WE <= 0;
                sram_C_RD <= 0;

                A_reg <= 0;
                for(idx = 0; idx < N_MAC; idx = idx + 1)begin
                    B_reg[idx] <= 0;
                    accum_reg[idx] <= 0;
                end
            end
            COMPUTE:begin //compute C[i][j*N_MAC : j*N_MAC+N_MAC-1]

                sram_C_CS <= 0;
                sram_C_RD <= 0;
                sram_C_WE <= 0;

                //propagate valid signals
                issue_valid <= (last_issue)? 0:1;
                data_valid <= issue_valid;
                mac_valid <= data_valid;

                //check for last cycle
                if(k_max == 0)
                    last_issue <= 1;
                else if(k==k_max-1)
                    last_issue <= 1;
                last_data <= last_issue;
                last_mac <= last_data;

                //update k-counter
                if(k<k_max) begin
                    k <= k+1;
                end

                //update accumulator reg with combinational mac output
                if(mac_valid) begin
                    for(idx = 0; idx < N_MAC; idx = idx + 1)
                        accum_reg[idx] <= mac_out[idx];
                end

                //copy the contents of SRAM outputs into input regs for MAC units
                if(data_valid) begin
                    A_reg <= sram_A_dout;
                    for(idx = 0; idx < N_MAC; idx = idx + 1)
                        B_reg[idx] <= sram_B_dout[idx*8 +: 8];
                end
            end
            WRITE:begin //write the contents of N_MAC mac units to sram_C, one mac unit value per cycle

                //iterate through each mac unit
                if(mac_id < N_MAC-1) begin
                    mac_id <= mac_id + 1;
                end

                //write to sram_C only for the valid columns of Matrix B
                if(j*N_MAC + mac_id < N_r) begin
                    sram_C_CS <= 1;
                    sram_C_RD <= 0;
                    sram_C_WE <= 1;
                    sram_C_addr <= C_base_r + i*N_r + j*N_MAC + mac_id;
                    sram_C_din <= accum_reg[mac_id];
                end
                else begin
                    sram_C_CS <= 0;
                    sram_C_RD <= 0;
                    sram_C_WE <= 0;                    
                end

                //after last write schedule, reset the registers and valid signals for next compute state or done state, update i,j counters
                if(mac_id == N_MAC-1) begin
                    mac_id <= 0;
                    A_reg <= 0;
                    for(idx = 0; idx < N_MAC; idx = idx + 1)begin
                        accum_reg[idx] <= 0; 
                        B_reg[idx] <= 0;   
                    end

                    data_valid <= 0;
                    mac_valid <= 0;
                    
                    if(k_max==0)
                        last_issue <= 1;
                    else
                        last_issue <= 0;
                    last_data <= 0;
                    last_mac <= 0;
                    
                    if(j<j_max)begin
                        j <= j+1;
                        k <= 0;
                        issue_valid <= 1;
                    end
                    else if(j==j_max && i<i_max)begin
                        j <= 0;
                        i <= i+1;
                        k <= 0;
                        issue_valid <= 1;
                    end
                    else begin
                        j <= 0;
                        i <= 0;
                        k <= 0;
                        issue_valid <= 0;
                    end
                end
            end
            DONE:begin //assert done = 1 and move to IDLE state

                sram_C_CS <= 0;
                sram_C_RD <= 0;
                sram_C_WE <= 0;

                done <= 1;            
            end
        endcase
    end
end


//combinational logic & next state logic
always @(*) begin

    sram_A_CS = (state == COMPUTE);
    sram_A_RD = (state == COMPUTE);
    sram_A_WE = 0;

    sram_B_CS = (state == COMPUTE);
    sram_B_RD = (state == COMPUTE);
    sram_B_WE = 0;

    sram_A_addr = A_base_r + i*K_r + k;
    sram_B_addr = B_base_r + j*K_r + k;

    for(idx = 0; idx < N_MAC; idx = idx + 1)
        accum_in[idx] = accum_reg[idx];

    write_done = (mac_id == N_MAC-1);
    
    next_state = state; //default

    case(state)
        IDLE:begin
            if(start)begin
                next_state = INIT;
            end
        end
        INIT:begin
            next_state = COMPUTE;
        end
        COMPUTE:begin
            if(mac_valid && last_mac)begin
                next_state = WRITE;
            end
        end
        WRITE:begin
            if(!write_done)begin
                next_state = WRITE;
            end
            else if(j==j_max && i==i_max)begin
                next_state = DONE;
            end
            else begin
                next_state = COMPUTE;
            end
        end
        DONE:begin
            next_state = IDLE;
        end        
    endcase
end
endmodule

tb/tb_gemm.v
`timescale 1ns/1ps

module tb_gemm;

reg clk;
reg rst_n;
reg start;

reg [9:0]  A_base;
reg [11:0] B_base;
reg [9:0]  C_base;

reg [15:0] M;
reg [15:0] K;
reg [15:0] N;

wire done;

integer i;
integer cycle_counter;
integer start_cycle;
integer end_cycle;

gemm_accelerator dut (
    .clk(clk),
    .rst_n(rst_n),
    .start(start),

    .A_base(A_base),
    .B_base(B_base),
    .C_base(C_base),

    .M(M),
    .K(K),
    .N(N),

    .done(done)
);

//////////////////////////////////////////////////
// Clock
//////////////////////////////////////////////////

initial begin
    clk = 0;
    forever #5 clk = ~clk;
end

initial cycle_counter = 0;

always @(posedge clk)
    cycle_counter = cycle_counter + 1;

//////////////////////////////////////////////////
// Wave dump
//////////////////////////////////////////////////

initial begin
    $dumpfile("waveforms/gemm.vcd");
    $dumpvars(0, tb_gemm);
end

//////////////////////////////////////////////////
// Cycle monitor
//////////////////////////////////////////////////

always @(posedge clk) begin
    $display("--------------------------------------------------");
    $display("t=%0t state=%0d done=%0d",
             $time,
             dut.state,
             dut.done);

    $display("i=%0d j=%0d k=%0d",
             dut.i,
             dut.j,
             dut.k);

    $display("issue=%0d data=%0d mac=%0d",
             dut.issue_valid,
             dut.data_valid,
             dut.mac_valid);

    $display("last_issue=%0d last_data=%0d last_mac=%0d",
             dut.last_issue,
             dut.last_data,
             dut.last_mac);

    $display("A_addr=%0d B_addr=%0d",
             dut.sram_A_addr,
             dut.sram_B_addr);

    $display("A_dout=%0d B_dout=%h",
             dut.sram_A_dout,
             dut.sram_B_dout);

//    $display("A_reg=%0d B_reg=%h",
//             dut.A_reg,
//             dut.B_reg);

    $display("accum0=%0d mac0=%0d",
             dut.accum_reg[0],
             dut.mac_out[0]);

    $display("C_WE=%0d C_addr=%0d C_din=%0d",
             dut.sram_C_WE,
             dut.sram_C_addr,
             dut.sram_C_din);
end

//////////////////////////////////////////////////
// Main test
//////////////////////////////////////////////////

initial begin

    rst_n  = 0;
    start  = 0;

    A_base = 0;
    B_base = 0;
    C_base = 0;

    M = 2;
    K = 2;
    N = 5;

    //--------------------------------------------------
    // Reset
    //--------------------------------------------------

    #20;
    rst_n = 1;

    //--------------------------------------------------
    // Initialize SRAM A
    //--------------------------------------------------
    dut.sram_A.SRAMs[3] = {
        8'd4
    };
    
    dut.sram_A.SRAMs[2] = {
        8'd3
    };

    dut.sram_A.SRAMs[1] = {
        8'd2
    };

    dut.sram_A.SRAMs[0] = {
        8'd1
    };

    //--------------------------------------------------
    // Initialize SRAM B
    //--------------------------------------------------

    dut.sram_B.SRAMs[1] = {
        8'd8,
        8'd7,
        8'd6,
        8'd5,
        8'd4,
        8'd3,
        8'd2,
        8'd1
    };
    
    dut.sram_B.SRAMs[0] = {    
        8'd8,
        8'd7,
        8'd6,
        8'd5,
        8'd4,
        8'd3,
        8'd2,
        8'd1
    };



    //--------------------------------------------------
    // Clear SRAM C
    //--------------------------------------------------

    for(i = 0; i < 16; i = i + 1)
        dut.sram_C.SRAMs[i] = 0;

    //--------------------------------------------------
    // Start accelerator
    //--------------------------------------------------

    @(posedge clk);
    start <= 1;
    start_cycle = cycle_counter;

    @(posedge clk);
    start <= 0;

    wait(done == 0);
    $display("Accelerator started");

    wait(done == 1);
    $display("Accelerator finished");

    $display("Layer 1 done");

    end_cycle = cycle_counter;

    $display("Total cycles = %0d", end_cycle - start_cycle);

    //--------------------------------------------------
    // Dump SRAM C
    //--------------------------------------------------

    $display("");
    $display("===== SRAM C CONTENTS =====");

    for(i = 0; i < 16; i = i + 1)
        $display("C[%0d] = %0d", i, dut.sram_C.SRAMs[i]);

    $display("");
    $finish;

end

endmodule

waveforms/gemm.vcd
$date
	Mon Jun 15 12:04:36 2026
$end
$version
	Icarus Verilog
$end
$timescale
	1ps
$end
$scope module tb_gemm $end
$var wire 1 ! done $end
$var reg 10 " A_base [9:0] $end
$var reg 12 # B_base [11:0] $end
$var reg 10 $ C_base [9:0] $end
$var reg 16 % K [15:0] $end
$var reg 16 & M [15:0] $end
$var reg 16 ' N [15:0] $end
$var reg 1 ( clk $end
$var reg 1 ) rst_n $end
$var reg 1 * start $end
$var integer 32 + cycle_counter [31:0] $end
$var integer 32 , end_cycle [31:0] $end
$var integer 32 - i [31:0] $end
$var integer 32 . start_cycle [31:0] $end
$scope module dut $end
$var wire 10 / A_base [9:0] $end
$var wire 12 0 B_base [11:0] $end
$var wire 10 1 C_base [9:0] $end
$var wire 16 2 K [15:0] $end
$var wire 16 3 M [15:0] $end
$var wire 16 4 N [15:0] $end
$var wire 1 ( clk $end
$var wire 1 ) rst_n $end
$var wire 1 * start $end
$var wire 32 5 sram_C_dout [31:0] $end
$var wire 64 6 sram_B_dout [63:0] $end
$var wire 8 7 sram_A_dout [7:0] $end
$var parameter 3 8 COMPUTE $end
$var parameter 3 9 DONE $end
$var parameter 3 : IDLE $end
$var parameter 3 ; INIT $end
$var parameter 32 < N_MAC $end
$var parameter 3 = WRITE $end
$var reg 10 > A_base_r [9:0] $end
$var reg 8 ? A_reg [7:0] $end
$var reg 12 @ B_base_r [11:0] $end
$var reg 10 A C_base_r [9:0] $end
$var reg 16 B K_r [15:0] $end
$var reg 16 C M_r [15:0] $end
$var reg 16 D N_r [15:0] $end
$var reg 1 E data_valid $end
$var reg 1 ! done $end
$var reg 16 F i [15:0] $end
$var reg 16 G i_max [15:0] $end
$var reg 1 H issue_valid $end
$var reg 16 I j [15:0] $end
$var reg 16 J j_max [15:0] $end
$var reg 16 K k [15:0] $end
$var reg 16 L k_max [15:0] $end
$var reg 1 M last_data $end
$var reg 1 N last_issue $end
$var reg 1 O last_mac $end
$var reg 4 P mac_id [3:0] $end
$var reg 1 Q mac_valid $end
$var reg 3 R next_state [2:0] $end
$var reg 1 S sram_A_CS $end
$var reg 1 T sram_A_RD $end
$var reg 1 U sram_A_WE $end
$var reg 10 V sram_A_addr [9:0] $end
$var reg 8 W sram_A_din [7:0] $end
$var reg 1 X sram_B_CS $end
$var reg 1 Y sram_B_RD $end
$var reg 1 Z sram_B_WE $end
$var reg 12 [ sram_B_addr [11:0] $end
$var reg 64 \ sram_B_din [63:0] $end
$var reg 1 ] sram_C_CS $end
$var reg 1 ^ sram_C_RD $end
$var reg 1 _ sram_C_WE $end
$var reg 10 ` sram_C_addr [9:0] $end
$var reg 32 a sram_C_din [31:0] $end
$var reg 3 b state [2:0] $end
$var reg 1 c write_done $end
$var integer 32 d idx [31:0] $end
$scope begin MAC_ARRAY[0] $end
$var parameter 2 e g $end
$scope module mac_inst $end
$var wire 8 f a [7:0] $end
$var wire 32 g accum_in [31:0] $end
$var wire 8 h b [7:0] $end
$var wire 32 i accum_out [31:0] $end
$upscope $end
$upscope $end
$scope begin MAC_ARRAY[1] $end
$var parameter 2 j g $end
$scope module mac_inst $end
$var wire 8 k a [7:0] $end
$var wire 32 l accum_in [31:0] $end
$var wire 8 m b [7:0] $end
$var wire 32 n accum_out [31:0] $end
$upscope $end
$upscope $end
$scope begin MAC_ARRAY[2] $end
$var parameter 3 o g $end
$scope module mac_inst $end
$var wire 8 p a [7:0] $end
$var wire 32 q accum_in [31:0] $end
$var wire 8 r b [7:0] $end
$var wire 32 s accum_out [31:0] $end
$upscope $end
$upscope $end
$scope begin MAC_ARRAY[3] $end
$var parameter 3 t g $end
$scope module mac_inst $end
$var wire 8 u a [7:0] $end
$var wire 32 v accum_in [31:0] $end
$var wire 8 w b [7:0] $end
$var wire 32 x accum_out [31:0] $end
$upscope $end
$upscope $end
$scope begin MAC_ARRAY[4] $end
$var parameter 4 y g $end
$scope module mac_inst $end
$var wire 8 z a [7:0] $end
$var wire 32 { accum_in [31:0] $end
$var wire 8 | b [7:0] $end
$var wire 32 } accum_out [31:0] $end
$upscope $end
$upscope $end
$scope begin MAC_ARRAY[5] $end
$var parameter 4 ~ g $end
$scope module mac_inst $end
$var wire 8 !" a [7:0] $end
$var wire 32 "" accum_in [31:0] $end
$var wire 8 #" b [7:0] $end
$var wire 32 $" accum_out [31:0] $end
$upscope $end
$upscope $end
$scope begin MAC_ARRAY[6] $end
$var parameter 4 %" g $end
$scope module mac_inst $end
$var wire 8 &" a [7:0] $end
$var wire 32 '" accum_in [31:0] $end
$var wire 8 (" b [7:0] $end
$var wire 32 )" accum_out [31:0] $end
$upscope $end
$upscope $end
$scope begin MAC_ARRAY[7] $end
$var parameter 4 *" g $end
$scope module mac_inst $end
$var wire 8 +" a [7:0] $end
$var wire 32 ," accum_in [31:0] $end
$var wire 8 -" b [7:0] $end
$var wire 32 ." accum_out [31:0] $end
$upscope $end
$upscope $end
$scope module sram_A $end
$var wire 10 /" Addr [9:0] $end
$var wire 1 S CS $end
$var wire 1 ( Clk $end
$var wire 1 T RD $end
$var wire 1 U WE $end
$var wire 8 0" dataIn [7:0] $end
$var parameter 32 1" ADR $end
$var parameter 32 2" DAT $end
$var parameter 32 3" DPTH $end
$var reg 8 4" dataOut [7:0] $end
$upscope $end
$scope module sram_B $end
$var wire 12 5" Addr [11:0] $end
$var wire 1 X CS $end
$var wire 1 ( Clk $end
$var wire 1 Y RD $end
$var wire 1 Z WE $end
$var wire 64 6" dataIn [63:0] $end
$var parameter 32 7" ADR $end
$var parameter 32 8" DAT $end
$var parameter 32 9" DPTH $end
$var reg 64 :" dataOut [63:0] $end
$upscope $end
$scope module sram_C $end
$var wire 10 ;" Addr [9:0] $end
$var wire 1 ] CS $end
$var wire 1 ( Clk $end
$var wire 1 ^ RD $end
$var wire 1 _ WE $end
$var wire 32 <" dataIn [31:0] $end
$var parameter 32 =" ADR $end
$var parameter 32 >" DAT $end
$var parameter 32 ?" DPTH $end
$var reg 32 @" dataOut [31:0] $end
$upscope $end
$upscope $end
$upscope $end
$enddefinitions $end
$comment Show the parameter values. $end
$dumpall
b10000000000 ?"
b100000 >"
b1010 ="
b1000000000000 9"
b1000000 8"
b1100 7"
b10000000000 3"
b1000 2"
b1010 1"
b111 *"
b110 %"
b101 ~
b100 y
b11 t
b10 o
b1 j
b0 e
b11 =
b1000 <
b1 ;
b0 :
b100 9
b10 8
$end
#0
$dumpvars
bx @"
b0 <"
b0 ;"
bx :"
bx 6"
b0 5"
bx 4"
bx 0"
b0 /"
b0 ."
b0 -"
b0 ,"
b0 +"
b0 )"
b0 ("
b0 '"
b0 &"
b0 $"
b0 #"
b0 ""
b0 !"
b0 }
b0 |
b0 {
b0 z
b0 x
b0 w
b0 v
b0 u
b0 s
b0 r
b0 q
b0 p
b0 n
b0 m
b0 l
b0 k
b0 i
b0 h
b0 g
b0 f
b1000 d
0c
b0 b
b0 a
b0 `
0_
0^
0]
bx \
b0 [
0Z
0Y
0X
bx W
b0 V
0U
0T
0S
b0 R
0Q
b0 P
0O
0N
0M
b0 L
b0 K
b0 J
b0 I
0H
b0 G
b0 F
0E
b0 D
b0 C
b0 B
b0 A
b0 @
b0 ?
b0 >
bx 7
bx 6
bx 5
b101 4
b10 3
b10 2
b0 1
b0 0
b0 /
bx .
bx -
bx ,
b0 +
0*
0)
0(
b101 '
b10 &
b10 %
b0 $
b0 #
b0 "
0!
$end
#5000
b1 +
b1000 d
1(
#10000
0(
#15000
b10 +
b1000 d
1(
#20000
0(
b10000 -
1)
#25000
b1 R
b1000 d
1*
b11 +
b10 .
1(
#30000
0(
#35000
b10 R
b1000 d
0*
b1 b
b101 D
b10 B
b10 C
b100 +
1(
#40000
0(
#45000
1Y
1X
1T
1S
1H
b1 L
b1 G
b10 b
b101 +
b1000 d
1(
#50000
0(
#55000
b1000 d
b1 [
b1 5"
b1 V
b1 /"
b1 K
1N
1E
b110 +
b100000000111000001100000010100000100000000110000001000000001 6
b100000000111000001100000010100000100000000110000001000000001 :"
b1 7
b1 4"
1(
#60000
0(
#65000
b1000 ."
b1000 -"
b111 )"
b111 ("
b110 $"
b110 #"
b101 }
b101 |
b100 x
b100 w
b11 s
b11 r
b10 n
b10 m
b1 i
b1 h
b1 ?
b1 f
b1 k
b1 p
b1 u
b1 z
b1 !"
b1 &"
b1 +"
1M
1Q
0H
b10 7
b10 4"
b111 +
b1000 d
1(
#70000
0(
#75000
b11 R
b1000 ,"
b111 '"
b110 ""
b101 {
b100 v
b11 q
b10 l
b1 g
b11 i
b110 n
b1001 s
b1100 x
b1111 }
b10010 $"
b10101 )"
b11000 ."
b10 ?
b10 f
b10 k
b10 p
b10 u
b10 z
b10 !"
b10 &"
b10 +"
1O
0E
b1000 +
b1000 d
1(
#80000
0(
#85000
b101000 ."
b11000 ,"
b100011 )"
b10101 '"
b11110 $"
b10010 ""
b11001 }
b1111 {
b10100 x
b1100 v
b1111 s
b1001 q
b1010 n
b110 l
b101 i
b11 g
0Y
0X
0T
0S
0Q
b11 b
b1001 +
b1000 d
1(
#90000
0(
#95000
b1000 d
b11 a
b11 <"
1_
1]
b1 P
b1010 +
1(
#100000
0(
#105000
b1000 d
b110 a
b110 <"
b1 `
b1 ;"
b10 P
b1011 +
1(
#110000
0(
#115000
b1000 d
b1001 a
b1001 <"
b10 `
b10 ;"
b11 P
b1100 +
1(
#120000
0(
#125000
b1000 d
b1100 a
b1100 <"
b11 `
b11 ;"
b100 P
b1101 +
1(
#130000
0(
#135000
b1000 d
b1111 a
b1111 <"
b100 `
b100 ;"
b101 P
b1110 +
1(
#140000
0(
#145000
b1000 d
0_
0]
b110 P
b1111 +
1(
#150000
0(
#155000
b10 R
1c
b1000 d
b111 P
b10000 +
1(
#160000
0(
#165000
0c
b0 ,"
b0 '"
b0 ""
b0 {
b0 v
b0 q
b0 l
b0 g
b0 [
b0 5"
b10 V
b10 /"
1Y
1X
1T
1S
1H
b0 K
b1 F
0O
0M
0N
b0 -"
b0 ("
b0 #"
b0 |
b0 w
b0 r
b0 m
b0 h
b0 i
b0 n
b0 s
b0 x
b0 }
b0 $"
b0 )"
b0 ."
b0 ?
b0 f
b0 k
b0 p
b0 u
b0 z
b0 !"
b0 &"
b0 +"
b0 P
b10 b
b10001 +
b1000 d
1(
#170000
0(
#175000
b1000 d
b1 [
b1 5"
b11 V
b11 /"
b1 K
1N
1E
b10010 +
b11 7
b11 4"
1(
#180000
0(
#185000
b11000 ."
b1000 -"
b10101 )"
b111 ("
b10010 $"
b110 #"
b1111 }
b101 |
b1100 x
b100 w
b1001 s
b11 r
b110 n
b10 m
b11 i
b1 h
b11 ?
b11 f
b11 k
b11 p
b11 u
b11 z
b11 !"
b11 &"
b11 +"
1M
1Q
0H
b100 7
b100 4"
b10011 +
b1000 d
1(
#190000
0(
#195000
b11 R
b11000 ,"
b10101 '"
b10010 ""
b1111 {
b1100 v
b1001 q
b110 l
b11 g
b111 i
b1110 n
b10101 s
b11100 x
b100011 }
b101010 $"
b110001 )"
b111000 ."
b100 ?
b100 f
b100 k
b100 p
b100 u
b100 z
b100 !"
b100 &"
b100 +"
1O
0E
b10100 +
b1000 d
1(
#200000
0(
#205000
b1011000 ."
b111000 ,"
b1001101 )"
b110001 '"
b1000010 $"
b101010 ""
b110111 }
b100011 {
b101100 x
b11100 v
b100001 s
b10101 q
b10110 n
b1110 l
b1011 i
b111 g
0Y
0X
0T
0S
0Q
b11 b
b10101 +
b1000 d
1(
#210000
0(
#215000
b1000 d
b111 a
b111 <"
b101 `
b101 ;"
1_
1]
b1 P
b10110 +
1(
#220000
0(
#225000
b1000 d
b1110 a
b1110 <"
b110 `
b110 ;"
b10 P
b10111 +
1(
#230000
0(
#235000
b1000 d
b10101 a
b10101 <"
b111 `
b111 ;"
b11 P
b11000 +
1(
#240000
0(
#245000
b1000 d
b11100 a
b11100 <"
b1000 `
b1000 ;"
b100 P
b11001 +
1(
#250000
0(
#255000
b1000 d
b100011 a
b100011 <"
b1001 `
b1001 ;"
b101 P
b11010 +
1(
#260000
0(
#265000
b1000 d
0_
0]
b110 P
b11011 +
1(
#270000
0(
#275000
b100 R
1c
b1000 d
b111 P
b11100 +
1(
#280000
0(
#285000
b0 R
0c
b0 ,"
b0 '"
b0 ""
b0 {
b0 v
b0 q
b0 l
b0 g
b0 [
b0 5"
b0 V
b0 /"
b0 K
b0 F
0O
0M
0N
b0 -"
b0 ("
b0 #"
b0 |
b0 w
b0 r
b0 m
b0 h
b0 i
b0 n
b0 s
b0 x
b0 }
b0 $"
b0 )"
b0 ."
b0 ?
b0 f
b0 k
b0 p
b0 u
b0 z
b0 !"
b0 &"
b0 +"
b0 P
b100 b
b11101 +
b1000 d
1(
#290000
0(
#295000
b1000 d
b10000 -
b11110 ,
b0 b
1!
b11110 +
1(
